peertube/AGENTS.md
peertube/__init__.py
peertube/_version.py
peertube/client.py
peertube/errors.py
peertube/types.py
peertube/api/__init__.py
peertube/api/shared_utils.py
peertube/api/abuses/__init__.py
peertube/api/abuses/abuses.py
peertube/api/abuses/get_abuses.py
peertube/api/abuses/get_my_abuses.py
peertube/api/abuses/my_abuses.py
peertube/api/account_blocks/__init__.py
peertube/api/account_blocks/api_blocklist_status.py
peertube/api/account_blocks/api_server_blocklist_accounts.py
peertube/api/account_blocks/api_server_blocklist_accounts_account_name.py
peertube/api/account_blocks/delete_api_v_1_server_blocklist_accounts_account_name.py
peertube/api/account_blocks/get_api_blocklist_status.py
peertube/api/account_blocks/get_api_server_blocklist_accounts.py
peertube/api/account_blocks/post_api_server_blocklist_accounts.py
peertube/api/accounts/__init__.py
peertube/api/accounts/account.py
peertube/api/accounts/account_followers.py
peertube/api/accounts/account_videos.py
peertube/api/accounts/accounts.py
peertube/api/accounts/api_accounts_name_ratings.py
peertube/api/accounts/get_account.py
peertube/api/accounts/get_account_followers.py
peertube/api/accounts/get_account_new.py
peertube/api/accounts/get_account_videos.py
peertube/api/accounts/get_account_videos_new.py
peertube/api/accounts/get_accounts.py
peertube/api/accounts/get_api_accounts_name_ratings.py
peertube/api/automatic_tags/__init__.py
peertube/api/automatic_tags/api_automatic_tags_accounts_account_name_available.py
peertube/api/automatic_tags/api_automatic_tags_policies_accounts_account_name_comments.py
peertube/api/automatic_tags/api_automatic_tags_server_available.py
peertube/api/automatic_tags/get_api_automatic_tags_server_available.py
peertube/api/automatic_tags/get_api_v_1_automatic_tags_accounts_account_name_available.py
peertube/api/automatic_tags/get_api_v_1_automatic_tags_policies_accounts_account_name_comments.py
peertube-1.1.1.dist-info/METADATA
peertube-1.1.1.dist-info/WHEEL
peertube-1.1.1.dist-info/licenses/LICENSE
peertube-1.1.1.dist-info/RECORD
