Metadata-Version: 2.4
Name: peertube
Version: 1.1.1
Summary: Python API wrappers for PeerTube using openapi-python-client.
Project-URL: Source Code, https://github.com/tonkintaylor/YOUR_REPOSITORY
Project-URL: Bug Tracker, https://github.com/tonkintaylor/YOUR_REPOSITORY/issues
Project-URL: Releases, https://github.com/tonkintaylor/YOUR_REPOSITORY/releases
Project-URL: Source Archive, https://github.com/tonkintaylor/YOUR_REPOSITORY/archive/4575391ac8ae4a4b69efe0ff2f8e338f3bece134.zip
Author-email: Bilbo Baggins <bbaggins@tonkintaylor.co.nz>
Maintainer-email: Data + Analytics <Sub-DisciplineData+AnalyticsStaff@tonkintaylor.co.nz>
License-Expression: MIT
License-File: LICENSE
Classifier: Programming Language :: Python :: 3 :: Only
Classifier: Programming Language :: Python :: 3.10
Classifier: Programming Language :: Python :: 3.11
Classifier: Programming Language :: Python :: 3.12
Classifier: Programming Language :: Python :: 3.13
Requires-Python: >=3.10
Requires-Dist: attrs>=22.2.0
Requires-Dist: httpx>=0.23.0
Requires-Dist: pydantic>=2.11.7
Requires-Dist: python-dateutil>=2.8.0
Requires-Dist: typing-extensions>=4.0.0
